fissionbox/__init__.py
fissionbox/cli/config.py
fissionbox/cli/main.py
fissionbox/cli/dataset/module.py
fissionbox/cli/reactor/module.py
fissionbox/cli/sample/module.py
fissionbox/cli/utils/env.py
fissionbox/core/__init__.py
fissionbox/core/reactor.py
fissionbox/core/sample.py
fissionbox/core/client/client.py
fissionbox/core/client/connection.py
fissionbox/core/client/reactor.py
fissionbox/core/client/sample.py
fissionbox-0.1.2.dist-info/licenses/LICENSE
fissionbox-0.1.2.dist-info/METADATA
fissionbox-0.1.2.dist-info/WHEEL
fissionbox-0.1.2.dist-info/entry_points.txt
fissionbox-0.1.2.dist-info/top_level.txt
fissionbox-0.1.2.dist-info/RECORD
